{"attributes": {}, "sections": {"TOP": "Painted Dogs015724t6152a0t236sh3dvhhftsn5drxdldlh866922013-05-08T23:30:49ZThe Dragon Demands5014364/* Season 1 */The '''Painted Dogs''' are one of the [[Hill tribe]]s of the [[Mountains of the Moon]].\n\n", "See also": "* [http://awoiaf.westeros.org/index.php/Painted_Dogs#The_Painted_Dogs The Painted Dogs at A Wiki of Ice and Fire]\n\n", "History": "===[[Season 1]]===\nThe Painted Dogs take part in the [[Battle of the Green Fork]].&lt;ref&gt;&quot;[[Baelor]]&quot;&lt;/ref&gt;\n\n"}, "title": "Painted Dogs"}