{"attributes": {"status": " :Category:Status: Dead", "family": [" Gregor Forrester - son", "Elissa Forrester - daughter-in-law", "Malcolm Branfield - son-in-law", "Rodrik Forrester - grandson", "Asher Forrester - grandson", "Mira Forrester - granddaughter", "Ethan Forrester - grandson", "Talia Forrester - granddaughter", "Ryon Forrester - grandson", "Talia Branfield - sister-in-law", "Branfield (Lord)"], "title": " Thorren Forrester", "season": " ''Game of Thrones: A Telltale Games Series''", "image": "Forrester mini shield.png", "allegiance": " House Forrester", "culture": " Northmen", "titles": " Lord of Ironrath", "link": "House ForresterCharacter", "mentioned": " &quot;Iron From Ice&quot;", "place": " Ironrath", "aka": " Thorren the Bold"}, "sections": {"TOP": "Thorren Forrester0299426j2jkeliys646jm85mur5kc2wylj4az1797222015-03-27T00:13:12ZJK1011x26248092{{Heraldry\n|image=Forrester mini shield.png\n|link=House Forrester\n}}\n{{Character\n|Title = Thorren Forrester\n|Season = ''[[Game of Thrones: A Telltale Games Series]]''\n|Mentioned = &quot;[[Iron From Ice]]&quot;\n|Titles = [[Lord of Ironrath]]\n|Aka = Thorren the Bold\n|Status = [[:Category:Status: Dead|Deceased]]\n|Place = [[Ironrath]]\n|Allegiance = [[House Forrester]]\n|Culture = [[Northmen]]\n|Family = {[[Gregor Forrester]]} - son&lt;br&gt;[[Elissa Forrester]] - daughter-in-law&lt;br&gt;[[Malcolm Branfield]] - son-in-law&lt;br&gt;[[Rodrik Forrester]] - grandson&lt;br&gt;[[Asher Forrester]] - grandson&lt;br&gt;[[Mira Forrester]] - granddaughter&lt;br&gt;{[[Ethan Forrester]]} - grandson&lt;br&gt;[[Talia Forrester]] - granddaughter&lt;br&gt;[[Ryon Forrester]] - grandson&lt;br&gt;{[[Talia Branfield]]} - sister-in-law&lt;br&gt;{[[Branfield (Lord)|Lord Branfield]]} - brother-in-law}}\n{{Quote|Your grandfather, Lord Thorren the Bold, who seized back the river valley from the Whitehills.|[[Ortengryn]] to [[Ethan Forrester]]|Iron From Ice}}\n'''Lord Thorren Forrester''' \u00e2&euro;&lsaquo;is an unseen character in\u00c2\u00a0''[[Game of Thrones: A Telltale Games Series]]''. He is long dead by the time the series begins, he is also the father of\u00c2\u00a0[[Gregor Forrester]].\n\n", "Family Tree": "{{House Forrester family tree}}\n\n", "Biography": "===Background===\nLord Thorren seized back the river valley from [[House Whitehill]].\n\nHe later fought in [[Robert's Rebellion]] and died at the [[Battle of the Trident]]. When he died his son Gregor succeeded him as Lord of Ironrath.\n===&quot;[[Iron From Ice]]&quot;===\nMaester\u00c2\u00a0Ortengryn\u00c2\u00a0mentions lord Thorren to Ethan that he was the one who seized back the river valleys from the Whitehills and that they called him Thorren the Bold.\n\n"}, "title": "Thorren Forrester"}